openai_tts_tool/__init__.py
openai_tts_tool/cli.py
openai_tts_tool/completion.py
openai_tts_tool/logging_config.py
openai_tts_tool/models.py
openai_tts_tool/utils.py
openai_tts_tool/voices.py
openai_tts_tool/commands/__init__.py
openai_tts_tool/commands/completion_commands.py
openai_tts_tool/commands/info_commands.py
openai_tts_tool/commands/model_commands.py
openai_tts_tool/commands/synthesize_commands.py
openai_tts_tool/commands/voice_commands.py
openai_tts_tool/core/__init__.py
openai_tts_tool/core/client.py
openai_tts_tool/core/synthesize.py
openai_tts_tool-0.1.0.dist-info/METADATA
openai_tts_tool-0.1.0.dist-info/WHEEL
openai_tts_tool-0.1.0.dist-info/entry_points.txt
openai_tts_tool-0.1.0.dist-info/licenses/LICENSE
openai_tts_tool-0.1.0.dist-info/RECORD
