Metadata-Version: 2.4
Name: openai-tts-tool
Version: 0.1.0
Summary: A CLI that provides tts using OpenAI
Project-URL: Homepage, https://github.com/dnvriend/openai-tts-tool
Project-URL: Repository, https://github.com/dnvriend/openai-tts-tool
Project-URL: Issues, https://github.com/dnvriend/openai-tts-tool/issues
Author-email: Dennis Vriend <dvriend@ilionx.com>
License: MIT
License-File: LICENSE
Keywords: audio,cli,openai,speech-synthesis,text-to-speech,tts
Classifier: Development Status :: 4 - Beta
Classifier: Intended Audience :: Developers
Classifier: License :: OSI Approved :: MIT License
Classifier: Programming Language :: Python :: 3
Classifier: Programming Language :: Python :: 3.14
Classifier: Topic :: Multimedia :: Sound/Audio :: Speech
Requires-Python: >=3.14
Requires-Dist: click>=8.1.7
Requires-Dist: openai>=1.40.0
Requires-Dist: pyaudio>=0.2.14
